irpf_cei/__init__.py
irpf_cei/__main__.py
irpf_cei/b3.py
irpf_cei/cei.py
irpf_cei/formatting.py
irpf_cei/py.typed
irpf_cei/responses.py
irpf_cei-3.5.2.dist-info/entry_points.txt
irpf_cei-3.5.2.dist-info/LICENSE.rst
irpf_cei-3.5.2.dist-info/WHEEL
irpf_cei-3.5.2.dist-info/METADATA
irpf_cei-3.5.2.dist-info/RECORD
