Metadata-Version: 2.1
Name: irpf-cei
Version: 3.5.2
Summary: Programa auxiliar gratuito para calcular custos de ações, ETFs e fundos imobiliários.
Home-page: https://github.com/staticdev/irpf-cei
License: MIT
Author: staticdev
Author-email: staticdev-support@protonmail.com
Requires-Python: >=3.8,<4.0
Classifier: License :: OSI Approved :: MIT License
Classifier: Programming Language :: Python :: 3
Classifier: Programming Language :: Python :: 3.10
Classifier: Programming Language :: Python :: 3.8
Classifier: Programming Language :: Python :: 3.9
Requires-Dist: click (>=7.1.1,<9.0.0)
Requires-Dist: inquirer (>=2.8.0,<3.0.0)
Requires-Dist: pandas (>=1.3.0,<2.0.0)
Requires-Dist: xlrd (>=1.2,<3.0)
Project-URL: Changelog, https://github.com/staticdev/irpf-cei/releases
Project-URL: Documentation, https://irpf-cei.readthedocs.io
Project-URL: Repository, https://github.com/staticdev/irpf-cei
